{"cameraMode":{"drawMode":0,"name":"Shaded","section":"Shading Mode"},"sceneLighting":true,"audioPlay":false,"sceneViewState":{"m_AlwaysRefresh":false,"showFog":true,"showSkybox":true,"showFlares":true,"showImageEffects":true,"showParticleSystems":true,"showVisualEffectGraphs":true,"m_FxEnabled":true},"in2DMode":false,"pivot":{"x":7.34677791595459,"y":-27.94324493408203,"z":9.469732284545899},"rotation":{"x":-0.5856808423995972,"y":-0.012888636440038681,"z":0.009314370341598988,"w":-0.81038898229599},"size":37.22610855102539,"orthographic":false}